fivetwofour_assignment_1/__init__.py
fivetwofour_assignment_1/fivetwofour_assignment_1.py
fivetwofour_assignment_1-0.1.0.dist-info/LICENSE
fivetwofour_assignment_1-0.1.0.dist-info/WHEEL
fivetwofour_assignment_1-0.1.0.dist-info/METADATA
fivetwofour_assignment_1-0.1.0.dist-info/RECORD
